django_apistar/__init__.py
django_apistar/apps.py
django_apistar/test.py
django_apistar/wsgi.py
django_apistar/authentication/__init__.py
django_apistar/authentication/components.py
django_apistar/authentication/hooks.py
django_apistar/authentication/models.py
django_apistar/authentication/schemas.py
django_apistar/authentication/views.py
django_apistar/authentication/migrations/0001_initial.py
django_apistar/authentication/migrations/__init__.py
django_apistar/static/apistar/css/base.css
django_apistar/static/apistar/css/bootstrap-theme.min.css
django_apistar/static/apistar/css/bootstrap.min.css
django_apistar/static/apistar/css/font-awesome-4.0.3.css
django_apistar/static/apistar/css/highlight.css
django_apistar/static/apistar/css/jquery.json-view.min.css
django_apistar/static/apistar/fonts/fontawesome-webfont.eot
django_apistar/static/apistar/fonts/fontawesome-webfont.svg
django_apistar/static/apistar/fonts/fontawesome-webfont.ttf
django_apistar/static/apistar/fonts/fontawesome-webfont.woff
django_apistar/static/apistar/fonts/glyphicons-halflings-regular.eot
django_apistar/static/apistar/fonts/glyphicons-halflings-regular.svg
django_apistar/static/apistar/fonts/glyphicons-halflings-regular.ttf
django_apistar/static/apistar/fonts/glyphicons-halflings-regular.woff
django_apistar/static/apistar/fonts/glyphicons-halflings-regular.woff2
django_apistar/static/apistar/img/favicon.ico
django_apistar/static/apistar/img/grid.png
django_apistar/static/apistar/img/gripper.png
django_apistar/static/apistar/img/logomarque-small-white.png
django_apistar/static/apistar/js/api.js
django_apistar/static/apistar/js/bootstrap.min.js
django_apistar/static/apistar/js/coreapi-0.1.0.js
django_apistar/static/apistar/js/highlight.pack.js
django_apistar/static/apistar/js/jquery-1.10.2.min.js
django_apistar/static/apistar/js/jquery.json-view.min.js
django_apistar-0.5.40.post0.dist-info/DESCRIPTION.rst
django_apistar-0.5.40.post0.dist-info/LICENSE.txt
django_apistar-0.5.40.post0.dist-info/METADATA
django_apistar-0.5.40.post0.dist-info/RECORD
django_apistar-0.5.40.post0.dist-info/WHEEL
django_apistar-0.5.40.post0.dist-info/metadata.json
django_apistar-0.5.40.post0.dist-info/top_level.txt
tests/tests/__init__.py
tests/tests/test_authentication.py
tests/tests/tests.py
