Metadata-Version: 2.0
Name: django-apistar
Version: 0.5.40-0
Summary: Django app for using API Star as frontend.
Home-page: https://github.com/lucianoratamero/django_apistar
Author: Luciano Ratamero
Author-email: luciano@ratamero.com
License: UNKNOWN
Keywords: apistar api rest django
Platform: UNKNOWN
Classifier: Development Status :: 4 - Beta
Classifier: Framework :: Django :: 1.8
Classifier: Framework :: Django :: 2.0
Classifier: License :: OSI Approved :: BSD License
Classifier: Intended Audience :: Developers
Classifier: Programming Language :: Python :: 3.6
Requires-Python: >=3.6,<3.7
Requires-Dist: apistar (>=0.4.0)
Requires-Dist: django (>=1.8)
